DeepLPTM/Simulations.py
DeepLPTM/Tutorial_deep-LPTM.ipynb
DeepLPTM/__init__.py
DeepLPTM/functions.py
DeepLPTM/main.py
DeepLPTM/model.py
DeepLPTM/ETM_raw/LICENSE
DeepLPTM/ETM_raw/README.md
DeepLPTM/ETM_raw/data.py
DeepLPTM/ETM_raw/etm.py
DeepLPTM/ETM_raw/main.py
DeepLPTM/ETM_raw/skipgram.py
DeepLPTM/ETM_raw/utils.py
DeepLPTM/ETM_raw/scripts/data_20ng.py
DeepLPTM/ETM_raw/scripts/data_preprocessing.py
DeepLPTM/ETM_raw/scripts/stops.txt
DeepLPTM/deepLPM_main/README.md
DeepLPTM/deepLPM_main/args.py
DeepLPTM/deepLPM_main/args_real_data.py
DeepLPTM/deepLPM_main/cora.py
DeepLPTM/deepLPM_main/input_data.py
DeepLPTM/deepLPM_main/model.py
DeepLPTM/deepLPM_main/preprocessing.py
DeepLPTM/deepLPM_main/train.py
deeplptm-0.0.1.dist-info/METADATA
deeplptm-0.0.1.dist-info/WHEEL
deeplptm-0.0.1.dist-info/licenses/LICENSE
deeplptm-0.0.1.dist-info/RECORD
