Metadata-Version: 2.1
Name: DeepLPTM
Version: 0.0.1
Summary: Implementation of the deep latent positions and topics model (Deep-LPTM)
Project-URL: Homepage, https://github.com/Remi-Boutin/DeepLPTM-package
Project-URL: Bug Tracker, https://github.com/Remi-Boutin/DeepLPTM-package/issues
Author-email: Remi Boutin <remi.boutin.stat@gmail.com>
License-File: LICENSE
Classifier: License :: OSI Approved :: MIT License
Classifier: Operating System :: OS Independent
Classifier: Programming Language :: Python :: 3
Requires-Python: >=3.7
